README.rst
setup.py
toiboi/__init__.py
toiboi.egg-info/PKG-INFO
toiboi.egg-info/SOURCES.txt
toiboi.egg-info/dependency_links.txt
toiboi.egg-info/top_level.txt