Metadata-Version: 1.1
Name: toiboi
Version: 0.0.0
Summary: TESS Object of Interest Binary Object Investigator
Home-page: https://github.com/pmaxted/toiboi
Author: P Maxted
Author-email: p.maxted@keele.ac.uk
License: GNU GPLv3
Keywords: astronomy
Platform: UNKNOWN
Classifier: Development Status :: 1 - Planning
Classifier: Intended Audience :: Science/Research
Classifier: Topic :: Scientific/Engineering
Classifier: License :: OSI Approved :: GNU General Public License v3 (GPLv3)
Classifier: Programming Language :: Python :: 3.6
